{
  "runId": "2026-01-14T21-54-43Z_7176f1",
  "status": "COMPLETE",
  "startedAt": "2026-01-14T21:54:43.805Z",
  "completedAt": "2026-01-14T21:54:50.834Z",
  "command": "run",
  "url": "https://example.com",
  "notes": "Run completed successfully",
  "metrics": {
    "learnMs": 0,
    "observeMs": 0,
    "detectMs": 0,
    "totalMs": 7029
  },
  "findingsCounts": {
    "HIGH": 0,
    "MEDIUM": 0,
    "LOW": 0,
    "UNKNOWN": 0
  },
  "digest": {
    "expectationsTotal": 5,
    "attempted": 5,
    "observed": 0,
    "silentFailures": 5,
    "coverageGaps": 0,
    "unproven": 0,
    "informational": 0
  }
}